rtry/__init__.py
rtry/_errors.py
rtry/_retry.py
rtry/_scheduler.py
rtry/_timeout.py
rtry/_types.py
rtry/py.typed
rtry/types/__init__.py
rtry-1.5.0.dist-info/LICENSE.txt
rtry-1.5.0.dist-info/METADATA
rtry-1.5.0.dist-info/WHEEL
rtry-1.5.0.dist-info/top_level.txt
rtry-1.5.0.dist-info/RECORD
