Metadata-Version: 2.1
Name: rtry
Version: 1.5.0
Summary: The easiest way to retry operations
Home-page: https://github.com/tsv1/rtry
Author: Nikita Tsvetkov
Author-email: tsv1@fastmail.com
License: MIT
Classifier: License :: OSI Approved :: MIT License
Classifier: Programming Language :: Python :: 3.7
Classifier: Programming Language :: Python :: 3.8
Classifier: Programming Language :: Python :: 3.9
Classifier: Programming Language :: Python :: 3.10
Classifier: Programming Language :: Python :: 3.11
Classifier: Typing :: Typed
Requires-Python: >=3.7
License-File: LICENSE.txt
